RandomShapeletClassifier.py
additional/ShapeletForestTest.csv
additional/__init__.py
additional/example.py
models/RandomShapeletClassifier.py
models/__init__.py
RandomShapelets-0.0.9.dist-info/LICENSE
RandomShapelets-0.0.9.dist-info/METADATA
RandomShapelets-0.0.9.dist-info/WHEEL
RandomShapelets-0.0.9.dist-info/top_level.txt
RandomShapelets-0.0.9.dist-info/RECORD
