Metadata-Version: 2.1
Name: RandomShapelets
Version: 0.0.9
Summary: A small package for time series classification
Home-page: UNKNOWN
Author: BennyPopp
Author-email: author@example.com
License: UNKNOWN
Platform: UNKNOWN
Classifier: Programming Language :: Python :: 3
Classifier: License :: OSI Approved :: MIT License
Classifier: Operating System :: OS Independent
